flexbox/__init__.py
flexbox/_core.cpython-39-darwin.so
flexbox/attributes.py
flexbox-0.0.2.dist-info/LICENSE
flexbox-0.0.2.dist-info/METADATA
flexbox-0.0.2.dist-info/WHEEL
flexbox-0.0.2.dist-info/top_level.txt
flexbox-0.0.2.dist-info/RECORD
