Metadata-Version: 2.1
Name: flexbox
Version: 0.0.2
Summary: FlexBox layout engine for Python
Home-page: https://github.com/tvogels/flexbox
Author: Thijs Vogels
License: MIT
Requires-Python: >=3.7
License-File: LICENSE
Requires-Dist: domtree (>=0.0.4)
Requires-Dist: typing-extensions (>=4)
Requires-Dist: numpy
Provides-Extra: test
Requires-Dist: pytest ; extra == 'test'
